uberduck/__init__.py
uberduck/client.py
uberduck/core/__init__.py
uberduck/core/api_error.py
uberduck/core/datetime_utils.py
uberduck/core/jsonable_encoder.py
uberduck/core/remove_none_from_headers.py
uberduck/environment.py
uberduck/errors/__init__.py
uberduck/errors/unprocessable_entity_error.py
uberduck/py.typed
uberduck/resources/__init__.py
uberduck/resources/backing_tracks/__init__.py
uberduck/resources/backing_tracks/client.py
uberduck/resources/reference_audios/__init__.py
uberduck/resources/reference_audios/client.py
uberduck/types/__init__.py
uberduck/types/add_reference_audio_response.py
uberduck/types/backing_track_options.py
uberduck/types/backing_track_options_genre.py
uberduck/types/convert_english_to_ipa_phonemes_request_phones.py
uberduck/types/dataset_speaker.py
uberduck/types/freestyle_request_backing_track.py
uberduck/types/g_2_p_response.py
uberduck/types/get_voice_data_request_mode.py
uberduck/types/get_voices_request_mode.py
uberduck/types/http_validation_error.py
uberduck/types/memberships.py
uberduck/types/mix_item.py
uberduck/types/mix_item_type.py
uberduck/types/reference_audio_response.py
uberduck/types/sample.py
uberduck/types/speak_status_response.py
uberduck/types/tts_request.py
uberduck/types/uuid.py
uberduck/types/validation_error.py
uberduck/types/voice_return.py
uberduck/types/voice_stats.py
fern_uberduck-0.0.6.dist-info/METADATA
fern_uberduck-0.0.6.dist-info/WHEEL
fern_uberduck-0.0.6.dist-info/RECORD
